MANIFEST.in
README.md
setup.cfg
setup.py
bin/sibis
sibis/__init__.py
sibis/logger.py
sibis/session.py
sibis.egg-info/PKG-INFO
sibis.egg-info/SOURCES.txt
sibis.egg-info/dependency_links.txt
sibis.egg-info/not-zip-safe
sibis.egg-info/requires.txt
sibis.egg-info/top_level.txt