Metadata-Version: 1.0
Name: sibis
Version: 0.0.2
Summary: Scalable Informatics for Biomedical Imaging Studies
Home-page: http://github.com/sibis-platform/sibis
Author: Nolan Nichols
Author-email: nolan.nichols@gmail.com
License: BSD
Platform: UNKNOWN
